setup.py
caffe/__init__.py
caffe/classifier.py
caffe/coord_map.py
caffe/detector.py
caffe/draw.py
caffe/io.py
caffe/model_libs.py
caffe/net_spec.py
caffe/pycaffe.py
caffe_ssd_x86.egg-info/PKG-INFO
caffe_ssd_x86.egg-info/SOURCES.txt
caffe_ssd_x86.egg-info/dependency_links.txt
caffe_ssd_x86.egg-info/requires.txt
caffe_ssd_x86.egg-info/top_level.txt