Metadata-Version: 1.0
Name: caffe-ssd-x86
Version: 1.0.0.0
Summary: Baidu Caffe SSD For Windows
Home-page: https://github.com/Baidu-AIP
Author: Baidu
Author-email: aipe@baidu.com
License: Apache License
Keywords: caffe,caff-ssd,windows
Platform: UNKNOWN
